advertising_locations/__about__.py
advertising_locations/__init__.py
advertising_locations/config.py
advertising_locations/genetic_optimizer.py
advertising_locations/main.py
advertising_locations/structures.py
advertising_locations-1.1.1.dist-info/METADATA
advertising_locations-1.1.1.dist-info/WHEEL
advertising_locations-1.1.1.dist-info/licenses/LICENSE
advertising_locations-1.1.1.dist-info/RECORD
